ostan/__init__.py
ostan/change_names.py
ostan/change_names_help_func.py
ostan/help_functions.py
ostan/land_codes.csv
ostan/mandatory_fields.csv
ostan/optional_fields.csv
ostan/data/land_codes.csv
ostan/data/mandatory_fields.csv
ostan/data/optional_fields.csv
ostan/resources/land_codes.csv
ostan/resources/mandatory_fields.csv
ostan/resources/optional_fields.csv
ostan-0.1.0.dist-info/LICENSE
ostan-0.1.0.dist-info/METADATA
ostan-0.1.0.dist-info/WHEEL
ostan-0.1.0.dist-info/top_level.txt
ostan-0.1.0.dist-info/RECORD
